MANIFEST.in
README.txt
lazy.sh
setup.py
./__init__.py
./bashcomp.py
./meta.py
bzr_bash_completion.egg-info/PKG-INFO
bzr_bash_completion.egg-info/SOURCES.txt
bzr_bash_completion.egg-info/dependency_links.txt
bzr_bash_completion.egg-info/top_level.txt