Metadata-Version: 1.0
Name: bzr-bash-completion
Version: 1.0.2
Summary: Generate bash command line completion function for bzr
Home-page: https://launchpad.net/bzr-bash-completion
Author: Martin von Gagern
Author-email: Martin.vGagern@gmx.net
License: GNU GPL v2
Keywords: bash bazaar bzr complete completion plugin shell vcs
Platform: UNKNOWN
Classifier: Development Status :: 5 - Production/Stable
Classifier: Environment :: Console
Classifier: Environment :: Plugins
Classifier: Intended Audience :: Developers
Classifier: License :: OSI Approved :: GNU General Public License (GPL)
Classifier: Operating System :: OS Independent
Classifier: Programming Language :: Python :: 2
Classifier: Programming Language :: Python
Classifier: Programming Language :: Unix Shell
Classifier: Topic :: Software Development :: Version Control
Classifier: Topic :: System :: Shells
